CHANGES.txt
MANIFEST.in
README.rst
TODO.txt
setup.py
mr/__init__.py
mr.igor.egg-info/PKG-INFO
mr.igor.egg-info/SOURCES.txt
mr.igor.egg-info/dependency_links.txt
mr.igor.egg-info/entry_points.txt
mr.igor.egg-info/namespace_packages.txt
mr.igor.egg-info/not-zip-safe
mr.igor.egg-info/requires.txt
mr.igor.egg-info/top_level.txt
mr/igor/__init__.py
mr/igor/checker.py
mr/igor/tests.py