Metadata-Version: 1.1
Name: mr.igor
Version: 1.4
Summary: Mr. Igor provides the parts you need to build your Frankenprogram.
Home-page: http://github.com/davisagli/mr.igor
Author: David Glick
Author-email: dglick@gmail.com
License: MIT
Keywords: python imports automatic
Platform: UNKNOWN
Classifier: Development Status :: 5 - Production/Stable
Classifier: Programming Language :: Python
Classifier: Environment :: Console
Classifier: Intended Audience :: Developers
Classifier: License :: OSI Approved :: MIT License
Classifier: Operating System :: OS Independent
Classifier: Topic :: Software Development :: Code Generators
